access_undenied_aws/__init__.py
access_undenied_aws/analysis.py
access_undenied_aws/cli.py
access_undenied_aws/common.py
access_undenied_aws/event.py
access_undenied_aws/event_permission_data.py
access_undenied_aws/iam_policy_data.py
access_undenied_aws/iam_utils.py
access_undenied_aws/organization_node.py
access_undenied_aws/organizations.py
access_undenied_aws/resource_policy_utils.py
access_undenied_aws/result_details.py
access_undenied_aws/results.py
access_undenied_aws/simulate_custom_policy_context_generator.py
access_undenied_aws/simulate_custom_policy_helper.py
access_undenied_aws/simulate_custom_policy_result_analyzer.py
access_undenied_aws/utils.py
access_undenied_aws/definitions/access_denied_message_patterns.json
access_undenied_aws/definitions/map.json
access_undenied_aws-0.1.5.dist-info/LICENSE
access_undenied_aws-0.1.5.dist-info/METADATA
access_undenied_aws-0.1.5.dist-info/NOTICE
access_undenied_aws-0.1.5.dist-info/WHEEL
access_undenied_aws-0.1.5.dist-info/entry_points.txt
access_undenied_aws-0.1.5.dist-info/top_level.txt
access_undenied_aws-0.1.5.dist-info/RECORD
