Metadata-Version: 2.1
Name: access-undenied-aws
Version: 0.1.5
Summary: Access Undenied on AWS by Ermetic - parses AWS AccessDenied CloudTrail events, explains the reasons for them, and offers actionable fixes.
Home-page: https://github.com/ermetic/access-undenied-aws
Author: Noam Dahan
Author-email: open.source@ermetic.com
License: UNKNOWN
Project-URL: Bug Tracker, https://github.com/ermetic/access-undenied-aws/issues
Platform: UNKNOWN
Classifier: Programming Language :: Python :: 3
Classifier: License :: OSI Approved :: Apache Software License
Classifier: Operating System :: OS Independent
Requires-Python: >=3.8
License-File: LICENSE
License-File: NOTICE
Requires-Dist: aws-error-utils (~=2.5.0)
Requires-Dist: boto3 (~=1.21.10)
Requires-Dist: botocore (~=1.24.8)
Requires-Dist: cachetools (~=5.0.0)
Requires-Dist: click (~=8.0.4)
Requires-Dist: click-log (~=0.3.2)
Requires-Dist: colorlog (~=6.6.0)
